termii_client/__init__.py
termii_client/base.py
termii_client/campaigns.py
termii_client/contacts.py
termii_client/insights.py
termii_client/messaging.py
termii_client/mixins.py
termii_client/phonebook.py
termii_client/sender_id.py
termii_client/token.py
termii_client-1.0.0.dist-info/LICENSE
termii_client-1.0.0.dist-info/METADATA
termii_client-1.0.0.dist-info/WHEEL
termii_client-1.0.0.dist-info/top_level.txt
termii_client-1.0.0.dist-info/RECORD
