Metadata-Version: 2.1
Name: termii-client
Version: 1.0.0
Summary: Python library for Termii API
Author: Gabriel Idenyi
License: MIT License
Project-URL: Homepage, https://github.com/idenyigabriel/termii
Project-URL: Documentation, https://github.com/idenyigabriel/termii/blob/main/README.md
Project-URL: Repository, https://github.com/idenyigabriel/termii
Project-URL: Issues, https://github.com/idenyigabriel/termii/issues
Project-URL: Changelog, https://github.com/idenyigabriel/termii/blob/main/CHANGELOG.md
Keywords: python,python3,termii
Classifier: Development Status :: 5 - Production/Stable
Classifier: Environment :: Web Environment
Classifier: Intended Audience :: Developers
Classifier: License :: OSI Approved :: MIT License
Classifier: Natural Language :: English
Classifier: Operating System :: OS Independent
Classifier: Programming Language :: Python
Classifier: Programming Language :: Python :: 3
Classifier: Programming Language :: Python :: 3 :: Only
Classifier: Programming Language :: Python :: 3.8
Classifier: Programming Language :: Python :: 3.9
Classifier: Programming Language :: Python :: 3.10
Classifier: Programming Language :: Python :: 3.11
Classifier: Programming Language :: Python :: 3.12
Classifier: Programming Language :: Python :: 3.13
Requires-Python: >=3.8
License-File: LICENSE
Requires-Dist: requests >=2.31.0
